graphviz_managed/__init__.py
graphviz_managed/custom.py
graphviz_managed/diagrams.py
graphviz_managed/logging.py
graphviz_managed/members.py
graphviz_managed-1.0.0.dist-info/LICENSE
graphviz_managed-1.0.0.dist-info/METADATA
graphviz_managed-1.0.0.dist-info/WHEEL
graphviz_managed-1.0.0.dist-info/top_level.txt
graphviz_managed-1.0.0.dist-info/zip-safe
graphviz_managed-1.0.0.dist-info/RECORD
