Metadata-Version: 2.1
Name: graphviz-managed
Version: 1.0.0
Summary: Manipulate Graphviz graphs in Python prior to rendering
Home-page: https://github.com/sio/graphviz-managed
License: Apache-2.0
Keywords: graphs,graphviz
Platform: UNKNOWN
Classifier: Environment :: Console
Classifier: Intended Audience :: Developers
Classifier: Intended Audience :: System Administrators
Classifier: License :: OSI Approved :: Apache Software License
Classifier: Programming Language :: Python :: 3
License-File: LICENSE
Requires-Dist: graphviz
Provides-Extra: diagrams
Requires-Dist: diagrams ; extra == 'diagrams'
